setup.py
Flask_SQLAlchemy_Session.egg-info/PKG-INFO
Flask_SQLAlchemy_Session.egg-info/SOURCES.txt
Flask_SQLAlchemy_Session.egg-info/dependency_links.txt
Flask_SQLAlchemy_Session.egg-info/requires.txt
Flask_SQLAlchemy_Session.egg-info/top_level.txt
flask_sqlalchemy_session/__init__.py