Metadata-Version: 1.1
Name: Flask-SQLAlchemy-Session
Version: 1.0
Summary: SQL Alchemy session scoped on Flask requests.
Home-page: http://github/dtheodor/flask-sqlalchemy-session
Author: Dimitris Theodorou
Author-email: dimitris.theodorou@gmail.com
License: UNKNOWN
Platform: UNKNOWN
Classifier: Development Status :: 5 - Production/Stable
Classifier: Intended Audience :: Developers
Classifier: Environment :: Web Environment
Classifier: License :: OSI Approved :: MIT License
Classifier: Programming Language :: Python :: 2.7
Classifier: Topic :: Internet :: WWW/HTTP :: Dynamic Content
Classifier: Topic :: Software Development :: Libraries :: Python Modules
